{
  "os":  "Windows-10-10.0.22631-SP0",
  "python":  "CPython 3.11.11",
  "startedAt":  "2025-02-06T08:39:52.864270Z",
  "program":  "Untitled.ipynb",
  "codePath":  "Untitled.ipynb",
  "git":  {
    "remote":  "https://github.com/K00LDUD3/SAiDL-Spring-Assignment-2025.git",
    "commit":  "136688ec8ea5dab3cdc5e5a523f75d709a08a857"
  },
  "email":  "tanushsrivatsa@gmail.com",
  "root":  "D:\\College Work\\Tanush\\SAiDL-Spring-Assignment-2025",
  "host":  "Tanush",
  "executable":  "C:\\Users\\91748\\.conda\\envs\\ml_stuff\\python.exe",
  "codePathLocal":  "Untitled.ipynb",
  "cpu_count":  8,
  "cpu_count_logical":  16,
  "gpu":  "NVIDIA GeForce RTX 3060 Laptop GPU",
  "gpu_count":  1,
  "disk":  {
    "/":  {
      "total":  "889973633024",
      "used":  "461079867392"
    }
  },
  "memory":  {
    "total":  "16498810880"
  },
  "cpu":  {
    "count":  8,
    "countLogical":  16
  },
  "gpu_nvidia":  [
    {
      "name":  "NVIDIA GeForce RTX 3060 Laptop GPU",
      "memoryTotal":  "6442450944",
      "cudaCores":  3840,
      "architecture":  "Ampere"
    }
  ],
  "cudaVersion":  "12.6"
}